{
  "cell_id": "round-robin_none_prefix_locality_ctx1024_s8_w12_c4_td200_f10_r2",
  "policy": "round-robin",
  "view": "none",
  "workload": "prefix_locality",
  "ctx_tokens": 1024,
  "n_steps": 8,
  "n_workflows": 12,
  "concurrent": 4,
  "duration_s": 120,
  "rep": 2,
  "freq_hz": 10,
  "tool_delay_ms": 200,
  "n_state_updates": 477,
  "ttft_p50": 198.296044,
  "ttft_p95": 381.131676,
  "ttft_p99": 467.110328,
  "tpot_p50": 92.88682375,
  "tpot_p95": 129.33960058333335,
  "workflow_completion_p50": 20673.96373,
  "workflow_completion_p95": 23590.046665,
  "workflow_completion_p99": 23671.917522,
  "cache_hit_rate": 0.9010229176319635,
  "cache_hits_delta": 75840.0,
  "cache_queries_delta": 84171.0,
  "n_total_steps": 84,
  "cross_instance_switches": 84,
  "same_instance_step_ratio": 0.0,
  "n_total_workflows": 12,
  "n_successful_workflows": 12,
  "n_failed_requests": 0,
  "load_stdev": 0.5137551524727939,
  "state_size_avg": 63,
  "state_size_p95": 63,
  "state_size_max": 63,
  "state_traffic_Bps": 5040,
  "dispatch_decision_p50": 16.011,
  "dispatch_decision_p95": 21.72,
  "dispatch_decision_p99": 55.957
}